stringmetric/__init__.py
stringmetric/distance/__init__.py
stringmetric/distance/hamming.py
stringmetric-0.1.0.dist-info/DESCRIPTION.rst
stringmetric-0.1.0.dist-info/METADATA
stringmetric-0.1.0.dist-info/RECORD
stringmetric-0.1.0.dist-info/WHEEL
stringmetric-0.1.0.dist-info/metadata.json
stringmetric-0.1.0.dist-info/top_level.txt
